fpquantize/e5m2.py
fpquantize-0.0.2.dist-info/METADATA
fpquantize-0.0.2.dist-info/WHEEL
fpquantize-0.0.2.dist-info/top_level.txt
fpquantize-0.0.2.dist-info/RECORD
