Metadata-Version: 2.4
Name: fpquantize
Version: 0.0.2
Summary: Floating point quantization
Author-email: Dan Jacobellis <danjacobellis@utexas.edu>
Classifier: Programming Language :: Python :: 3
Classifier: Operating System :: OS Independent
Requires-Python: >=3.6
Requires-Dist: torch
